{
   "graph_json" : {
      "extras" : {
         "directed" : false,
         "bipartite" : true
      },
      "edges" : [
         {
            "s" : 0,
            "t" : 1
         }
      ],
      "nodes" : [
         {
            "coords" : [
               0.125,
               -0.125,
               0
            ],
            "degree_in" : 1,
            "label" : "珊瑚婚",
            "score" : 0.5
         },
         {
            "coords" : [
               -0.125,
               0.125,
               0
            ],
            "degree_in" : 1,
            "label" : "碧玉婚",
            "score" : 0.5
         }
      ]
   },
   "clustering_json" : [
      {
         "labels" : [
            [
               "珊瑚婚",
               1
            ],
            [
               "碧玉婚",
               1
            ]
         ]
      }
   ]
}
